.gitignore
LICENSE
MANIFEST.in
README.md
pyproject.toml
requirements.txt
setup.py
.github/workflows/pypi-publish.yml
.github/workflows/python-tests.yml
optuna_fast_fanova/__init__.py
optuna_fast_fanova/_evaluator.py
optuna_fast_fanova/_fanova.pyx
optuna_fast_fanova/_version.py
optuna_fast_fanova.egg-info/PKG-INFO
optuna_fast_fanova.egg-info/SOURCES.txt
optuna_fast_fanova.egg-info/dependency_links.txt
optuna_fast_fanova.egg-info/requires.txt
optuna_fast_fanova.egg-info/top_level.txt
venv/bin/readelf.py
venv/bin/rst2html.py
venv/bin/rst2html4.py
venv/bin/rst2html5.py
venv/bin/rst2latex.py
venv/bin/rst2man.py
venv/bin/rst2odt.py
venv/bin/rst2odt_prepstyles.py
venv/bin/rst2pseudoxml.py
venv/bin/rst2s5.py
venv/bin/rst2xetex.py
venv/bin/rst2xml.py
venv/bin/rstpep2html.py