Metadata-Version: 2.1
Name: optuna-fast-fanova
Version: 0.0.4
Summary: Cython accelerated fANOVA implementation for Optuna
Home-page: https://github.com/optuna/optuna-fast-fanova
Author-email: Masashi Shibata <mshibata@preferred.jp>
License: MIT License
Project-URL: Homepage, https://github.com/optuna/optuna-fast-fanova
Project-URL: Sources, https://github.com/optuna/optuna-fast-fanova
Project-URL: Bug Tracker, https://github.com/optuna/optuna-fast-fanova/issues
Platform: UNKNOWN
Classifier: Development Status :: 2 - Pre-Alpha
Classifier: Intended Audience :: Science/Research
Classifier: Intended Audience :: Developers
Classifier: License :: OSI Approved :: MIT License
Classifier: Programming Language :: Python :: 3
Classifier: Programming Language :: Python :: 3.7
Classifier: Programming Language :: Python :: 3.8
Classifier: Programming Language :: Python :: 3.9
Classifier: Programming Language :: Python :: 3.10
Classifier: Programming Language :: Python :: 3 :: Only
Classifier: Topic :: Scientific/Engineering
Classifier: Topic :: Scientific/Engineering :: Mathematics
Classifier: Topic :: Scientific/Engineering :: Artificial Intelligence
Classifier: Topic :: Software Development
Classifier: Topic :: Software Development :: Libraries
Classifier: Topic :: Software Development :: Libraries :: Python Modules
Requires-Python: >=3.7
License-File: LICENSE
